lll_taskmanager/__init__.py
lll_taskmanager/autoencoder_utils.py
lll_taskmanager/task_manager.py
lll_taskmanager-0.1.4.dist-info/LICENSE.txt
lll_taskmanager-0.1.4.dist-info/METADATA
lll_taskmanager-0.1.4.dist-info/WHEEL
lll_taskmanager-0.1.4.dist-info/RECORD
