Metadata-Version: 2.3
Name: lll_taskmanager
Version: 0.1.4
Summary: Unsupervised task detection in lifelong learning systems using autoencoders for task similarity detection and statistical analysis.
License: CC BY 4.0
Author: Ferdinand Koenig
Author-email: ferdinand@koenix.de
Requires-Python: >=3.9,<3.11
Classifier: Programming Language :: Python
Classifier: Programming Language :: Python :: 3
Classifier: Programming Language :: Python :: 3.9
Classifier: Programming Language :: Python :: 3.10
Classifier: Operating System :: OS Independent
Classifier: Intended Audience :: Developers
Classifier: Intended Audience :: Science/Research
Classifier: Topic :: Scientific/Engineering
Classifier: Topic :: Software Development :: Libraries
Requires-Dist: keras (>=2.11.0,<2.12) ; sys_platform == "darwin"
Requires-Dist: keras (>=2.11.0,<2.12) ; sys_platform == "linux"
Requires-Dist: keras (>=2.11.0,<2.12) ; sys_platform == "win32"
Requires-Dist: keras-tuner (>=1.4.7,<2.0.0)
Requires-Dist: numpy (>=1.21.6,<1.23)
Requires-Dist: scikit-learn (>=1.6.1,<2.0.0)
Requires-Dist: scipy (>=1.13.1,<2.0.0)
Requires-Dist: tensorflow (==2.11) ; sys_platform == "linux"
Requires-Dist: tensorflow (==2.11) ; sys_platform == "win32"
Requires-Dist: tensorflow-io-gcs-filesystem (==0.31.0) ; sys_platform == "win32"
Requires-Dist: tensorflow-io-gcs-filesystem ; sys_platform == "linux"
Requires-Dist: tensorflow-macos (==2.11.0) ; sys_platform == "darwin"
Requires-Dist: tensorflow-metal (==0.7.0) ; sys_platform == "darwin"
